datasette_queries/__init__.py
datasette_queries/templates/_datasette_queries_top.html
datasette_queries-0.1.2.dist-info/licenses/LICENSE
datasette_queries-0.1.2.dist-info/METADATA
datasette_queries-0.1.2.dist-info/WHEEL
datasette_queries-0.1.2.dist-info/entry_points.txt
datasette_queries-0.1.2.dist-info/top_level.txt
datasette_queries-0.1.2.dist-info/RECORD
