Metadata-Version: 2.4
Name: datasette-queries
Version: 0.1.2
Summary: Save SQL queries in Datasette
Author: Simon Willison
License-Expression: Apache-2.0
Project-URL: Homepage, https://github.com/datasette/datasette-queries
Project-URL: Changelog, https://github.com/datasette/datasette-queries/releases
Project-URL: Issues, https://github.com/datasette/datasette-queries/issues
Project-URL: CI, https://github.com/datasette/datasette-queries/actions
Classifier: Framework :: Datasette
Requires-Python: >=3.9
License-File: LICENSE
Requires-Dist: datasette>=1.0a16
Requires-Dist: sqlite-migrate
Provides-Extra: test
Requires-Dist: pytest; extra == "test"
Requires-Dist: pytest-asyncio; extra == "test"
Dynamic: license-file
